{"01073":[0.0,0.0,0.0,0.0,0.0,0.0,0.0,0.0,0.0,0.0,0.0,0.0,0.0,0.0,0.0,0.0,0.0,0.0,0.0,0.0,0.0,0.0,0.0,0.0,0.0,null,null,null],"01101":[null,null,null,null,null,null,null,null,0.0,null,null,null,null,null,null,null,null,null,null,null,null,null,null,null,null,null,null,null],"04013":[0.0,0.0,0.0,null,null,0.0,null,null,null,null,null,null,0.0,null,null,null,null,null,null,null,null,null,null,null,null,null,null,null],"05119":[null,null,null,null,null,0.0,0.0,0.0,null,null,null,0.0,null,null,null,null,null,null,null,null,null,null,null,null,null,null,null,null],"06017":[0.0,0.01,null,0.0,0.0,0.0,null,0.0,0.0,null,0.01,0.01,0.01,0.01,0.0,null,0.01,0.01,0.01,null,null,null,null,null,null,null,null,null],"06019":[null,null,null,null,null,null,null,null,null,null,null,null,null,null,null,null,null,0.0,0.0,0.0,0.0,0.0,0.0,0.0,0.0,0.0,0.0,0.0],"06025":[0.0,null,null,0.0,null,0.0,0.0,0.0,null,null,null,0.0,null,null,0.0,0.0,null,0.0,0.0,null,null,null,null,null,0.0,null,null,null],"06031":[null,null,null,null,null,null,null,0.0,null,null,null,0.0,0.0,0.0,0.0,0.0,0.0,0.0,0.0,0.0,0.0,0.0,0.0,0.0,0.01,0.0,0.0,0.0],"06037":[0.0,0.0,0.0,0.0,0.0,0.0,0.0,0.0,0.0,0.0,0.0,0.0,0.0,0.0,0.0,0.0,0.0,0.0,0.0,0.0,0.0,0.0,0.0,0.0,0.0,0.0,0.0,0.0],"06059":[0.0,0.0,0.0,0.0,0.0,0.0,0.0,null,null,null,null,null,0.0,0.0,0.0,0.0,0.0,0.0,0.0,0.0,0.0,0.0,0.0,0.0,0.0,0.0,0.0,0.0],"06067":[0.0,0.0,0.0,0.0,0.0,0.0,0.0,0.0,0.0,null,null,null,0.0,null,0.0,null,null,null,null,null,null,null,null,null,null,null,null,null],"06073":[0.0,0.0,0.0,0.0,0.0,0.0,0.0,0.0,0.0,0.0,0.0,0.0,0.0,0.0,0.0,0.0,0.0,0.0,0.0,0.0,0.0,0.0,0.0,null,0.0,0.0,0.0,0.0],"06075":[0.0,0.0,0.0,0.0,0.0,0.0,0.0,0.0,0.0,null,null,null,null,null,null,null,null,null,null,null,null,null,null,null,null,null,null,null],"06107":[null,0.0,0.0,0.0,0.0,0.0,0.0,0.0,0.0,0.0,0.0,0.0,0.0,0.0,0.0,0.0,0.0,0.0,0.0,0.0,null,0.0,null,null,0.0,0.0,0.0,null],"06115":[0.01,0.01,0.01,0.01,0.01,0.01,0.0,null,null,null,null,null,null,null,null,null,null,null,null,null,null,null,null,null,null,null,null,null],"08005":[null,null,null,null,null,null,null,null,null,null,null,null,null,null,null,null,null,null,null,null,null,null,null,null,null,null,0.0,null],"08041":[null,0.0,0.0,null,null,null,null,null,null,null,null,null,null,null,0.0,null,null,null,null,null,null,null,null,null,null,null,null,null],"08083":[0.01,null,null,null,null,null,null,null,null,null,null,null,null,null,null,null,null,null,null,null,null,null,null,null,null,null,null,null],"10003":[0.0,0.0,0.0,0.0,0.0,0.0,0.0,0.0,0.0,0.0,0.0,0.0,0.0,0.0,0.0,0.0,0.0,0.0,0.0,0.0,0.0,0.0,0.0,0.0,0.0,0.0,0.0,0.0],"11001":[0.0,0.0,0.0,0.0,null,0.0,0.0,0.0,null,null,null,null,0.0,null,null,null,null,null,null,null,null,null,null,null,null,null,null,null],"12001":[null,null,null,null,null,null,null,null,null,null,null,null,null,null,null,0.0,0.0,0.0,null,0.0,0.0,null,null,null,null,null,null,null],"12009":[null,null,null,null,null,null,null,0.0,0.0,0.0,0.0,0.0,0.0,0.0,0.0,null,null,null,null,null,null,null,null,null,null,null,null,null],"12011":[null,null,null,0.0,0.0,0.0,0.0,0.0,0.0,0.0,0.0,0.0,0.0,0.0,0.0,0.0,0.0,0.0,0.0,0.0,0.0,0.0,0.0,0.0,0.0,0.0,0.0,0.0],"12031":[null,null,null,null,null,null,null,null,null,null,null,null,0.0,null,0.0,null,null,null,0.0,null,null,null,null,null,null,null,null,null],"12033":[null,null,null,null,null,0.0,0.0,null,0.0,null,null,null,null,null,null,null,null,null,null,null,null,null,null,null,null,null,null,null],"12057":[null,null,null,0.0,0.0,0.0,0.0,0.0,0.0,0.0,null,0.0,0.0,null,0.0,0.0,null,0.0,0.0,0.0,0.0,0.0,0.0,0.0,0.0,0.0,0.0,null],"12061":[null,null,null,null,null,null,null,null,null,null,null,null,null,null,null,null,null,0.0,null,0.0,0.0,0.0,0.0,null,null,null,null,null],"12073":[null,null,null,null,null,0.0,null,null,null,null,null,null,null,null,null,null,null,null,null,null,null,null,null,null,null,null,null,null],"12095":[null,null,null,null,0.0,0.0,0.0,0.0,0.0,0.0,0.0,0.0,null,null,null,0.0,0.0,null,null,null,null,null,null,null,null,null,null,null],"12103":[null,null,null,null,0.0,null,0.0,0.0,0.0,0.0,0.0,null,null,null,null,null,null,null,null,null,null,null,null,null,0.0,null,0.0,0.0],"12105":[null,null,null,null,null,null,null,0.0,null,null,null,null,null,null,null,null,null,null,null,null,null,null,null,null,null,null,null,null],"12113":[null,null,null,null,0.0,0.0,0.0,0.0,0.0,0.0,0.03,null,null,null,null,null,null,null,null,null,null,null,null,null,null,null,null,null],"13031":[0.01,0.01,0.01,0.01,0.01,0.01,0.01,0.0,0.0,0.0,null,0.01,0.01,0.01,null,null,null,null,0.0,null,0.01,0.01,0.01,0.0,null,null,null,null],"13051":[0.01,0.02,0.01,0.01,0.01,0.01,0.01,0.01,0.01,0.01,0.01,0.01,0.01,0.01,0.0,0.01,0.0,0.0,0.01,0.01,0.0,0.01,0.01,0.0,0.0,0.0,0.0,0.0],"13059":[null,null,null,null,null,null,null,null,null,null,null,null,null,null,null,0.0,null,null,null,null,null,null,null,null,null,null,null,null],"13089":[0.01,0.01,0.01,0.01,0.01,0.01,0.01,0.01,0.01,0.0,0.01,0.0,0.01,0.01,0.0,0.0,0.0,0.0,0.0,0.0,0.0,0.0,0.0,0.0,0.0,0.0,0.0,0.0],"13121":[0.0,0.0,0.0,0.0,0.0,0.0,0.0,0.0,0.0,0.0,0.0,0.0,0.0,0.0,0.0,0.0,null,null,0.0,null,null,null,null,null,null,null,null,null],"13139":[null,null,null,null,null,null,null,null,null,null,null,null,null,0.0,0.0,null,null,0.0,0.0,0.0,0.0,0.0,0.0,null,null,null,null,0.0],"13151":[0.01,0.01,0.0,0.0,null,0.0,0.0,0.0,0.0,null,null,null,null,null,null,null,null,null,null,null,null,null,null,null,null,null,null,null],"13153":[0.0,null,0.0,0.0,null,null,null,null,null,null,null,null,null,null,null,null,null,null,null,null,null,null,null,null,null,null,null,null],"13275":[null,0.01,null,null,null,null,null,null,null,null,null,null,null,null,null,null,null,null,null,null,null,null,null,null,null,null,null,null],"13305":[0.02,0.01,0.01,0.01,null,null,0.02,0.01,0.01,null,null,null,null,null,null,null,null,null,null,null,null,null,null,0.01,null,null,null,null],"17001":[null,null,null,0.0,0.0,null,0.0,0.0,0.01,null,0.0,0.01,0.01,0.0,0.01,0.01,0.0,0.01,0.01,0.0,0.01,0.01,0.01,0.01,0.01,0.01,0.01,null],"17031":[0.0,0.0,0.0,0.0,0.0,0.0,0.0,0.0,0.0,0.0,0.0,null,0.0,0.0,0.0,0.0,0.0,0.0,null,null,0.0,null,null,null,null,null,null,null],"17043":[0.0,0.0,0.0,0.0,0.01,0.0,0.01,0.0,0.0,0.0,0.0,0.0,0.0,0.0,0.0,0.0,0.0,0.0,0.0,0.0,0.0,0.0,0.0,0.0,0.0,0.0,0.0,0.0],"17097":[null,null,null,0.0,0.0,null,0.0,0.0,null,0.0,0.0,0.0,0.0,0.0,0.0,0.0,0.0,0.0,0.0,0.0,0.0,0.0,0.0,0.0,0.0,0.0,0.0,null],"17103":[null,null,null,0.01,0.01,null,null,null,null,null,null,null,null,null,null,null,null,null,null,null,null,null,null,null,null,null,null,null],"17111":[null,null,null,null,null,null,null,null,null,0.0,0.0,0.0,0.0,0.0,0.0,null,null,null,null,null,null,null,null,null,null,null,null,null],"17115":[null,null,null,null,null,null,null,null,null,null,null,null,null,null,null,null,null,null,null,null,null,0.0,0.01,0.0,0.01,0.01,0.01,null],"17163":[0.0,0.0,null,null,0.0,null,null,null,null,null,null,null,null,null,null,null,null,null,null,null,null,null,null,null,null,null,null,null],"17167":[null,null,null,null,null,null,null,null,null,null,null,null,null,null,null,null,null,null,null,null,0.0,0.01,null,0.0,null,0.0,0.01,null],"18003":[null,null,null,null,null,null,null,null,null,null,null,null,null,null,null,null,null,null,null,null,null,null,null,0.0,null,null,null,null],"18053":[null,null,0.0,null,null,null,null,null,null,null,null,null,null,null,null,null,null,null,null,0.01,0.01,null,null,0.01,0.02,0.01,null,null],"18059":[null,null,null,null,null,null,null,null,null,null,null,null,null,null,0.01,null,null,null,null,null,null,null,null,null,null,null,null,null],"18071":[null,null,null,null,null,null,0.01,null,null,null,null,null,null,null,null,null,null,null,null,null,null,null,null,null,null,null,null,null],"18089":[null,null,null,0.0,null,null,0.0,null,null,null,null,null,null,null,null,null,null,null,null,null,null,null,null,null,null,null,null,null],"18097":[0.0,0.0,0.0,0.0,0.0,0.0,0.0,0.0,0.0,0.0,0.0,0.0,0.0,0.0,0.0,0.0,0.0,0.0,0.0,null,null,null,null,null,null,null,null,null],"18123":[null,null,0.01,null,null,null,null,0.02,null,null,null,0.02,null,null,null,null,null,null,null,null,null,null,null,null,null,null,null,null],"18177":[null,null,null,null,null,null,null,0.0,0.0,null,null,null,null,null,null,null,null,null,null,null,null,null,null,null,null,null,null,null],"19113":[null,null,0.0,null,null,null,0.0,null,null,null,null,0.0,null,null,null,null,null,null,null,null,null,null,null,null,null,null,null,null],"19163":[0.0,0.0,0.0,0.0,0.0,0.0,0.0,0.0,0.0,null,0.0,0.0,0.0,0.0,0.0,0.0,0.0,0.0,0.0,0.0,0.0,0.0,0.0,0.0,null,null,null,null],"20091":[0.01,0.01,0.01,0.01,0.01,0.01,0.01,0.01,0.01,0.0,0.01,0.01,0.0,0.01,0.0,0.0,0.0,0.01,0.0,0.0,0.0,0.0,0.0,0.0,0.0,0.0,0.0,0.0],"20177":[0.0,0.01,0.01,0.01,0.01,0.0,0.01,0.01,0.01,0.0,null,null,null,null,null,null,null,null,0.0,null,null,null,null,null,null,null,null,null],"21035":[0.13,0.12,0.09,0.05,0.02,0.02,null,null,null,null,null,null,null,null,null,null,null,null,null,null,null,null,null,null,null,null,null,null],"21049":[0.02,0.02,0.03,0.0,0.01,0.01,0.0,null,0.01,0.0,null,0.03,0.01,0.01,null,0.0,null,0.0,null,null,0.0,0.01,null,null,null,null,null,null],"21059":[null,null,null,null,null,null,null,null,null,null,null,null,null,null,null,null,0.0,0.0,0.0,null,null,0.0,0.0,0.0,null,0.0,0.0,0.0],"21067":[0.02,0.02,0.03,0.02,0.02,0.02,0.02,0.01,0.01,0.0,0.01,0.02,0.02,0.01,0.01,0.01,0.01,0.01,0.01,0.01,0.01,0.0,0.01,0.01,0.01,0.01,0.0,0.0],"21107":[null,null,null,null,null,null,0.0,null,null,null,null,null,null,null,null,null,null,null,null,null,null,null,null,null,null,null,null,null],"21111":[null,null,0.0,0.0,null,0.0,null,0.0,0.0,0.0,null,0.0,null,0.0,null,0.0,null,null,null,null,null,null,null,0.0,null,null,null,null],"21137":[null,null,null,null,null,null,0.02,0.01,null,null,null,null,null,0.01,null,null,null,null,null,null,null,null,null,null,null,null,null,null],"21151":[0.0,null,0.0,null,null,null,0.0,null,null,null,null,null,null,null,null,null,null,null,null,null,null,null,null,null,null,null,null,null],"21155":[0.03,0.0,0.01,null,null,0.01,0.02,null,null,null,0.01,null,null,null,null,0.01,null,null,null,null,null,null,null,null,null,0.01,null,null],"21185":[null,null,0.0,null,null,null,null,null,null,null,null,null,null,null,null,null,null,null,null,null,null,null,null,null,null,null,null,null],"21205":[null,null,null,null,0.01,0.05,0.04,0.02,0.05,0.04,0.08,0.03,0.02,null,null,null,null,null,null,null,null,null,null,null,null,null,null,null],"21209":[0.01,0.03,0.01,0.02,0.02,0.01,null,null,null,null,null,null,null,null,null,null,null,null,null,null,null,null,null,null,null,null,null,null],"21231":[0.07,0.06,0.06,0.05,0.05,0.04,0.04,0.03,0.02,0.01,0.03,0.04,0.04,0.04,0.04,0.02,0.01,0.01,0.01,null,null,null,null,null,null,null,null,null],"21235":[0.0,0.01,null,null,null,null,null,null,null,null,null,null,null,null,null,null,null,null,null,null,null,null,null,null,null,null,null,null],"22019":[null,null,null,null,0.0,null,null,null,null,null,null,null,null,null,null,null,null,null,null,null,null,null,null,null,null,null,null,null],"22053":[null,null,null,null,null,null,null,null,null,null,null,null,null,null,null,0.0,null,null,null,null,null,null,0.0,0.0,0.0,null,null,null],"22109":[0.0,0.0,null,0.0,0.0,0.01,0.0,0.0,0.0,0.0,0.0,0.0,0.0,0.0,0.0,0.0,0.0,0.01,0.0,null,0.0,0.0,0.0,null,null,null,null,null],"23003":[null,null,0.0,0.0,0.0,0.0,0.0,null,null,null,null,null,null,null,null,null,null,null,null,null,0.0,0.0,null,null,null,null,0.0,0.0],"24003":[null,0.0,0.0,0.0,0.0,0.0,0.0,0.0,0.0,0.0,0.0,0.0,0.0,0.0,0.0,0.0,0.0,0.0,0.0,0.0,0.0,0.0,0.0,0.0,0.0,0.0,0.0,0.0],"24005":[0.0,0.0,0.0,0.0,0.0,0.0,0.0,0.0,0.0,0.0,0.0,0.0,0.0,0.0,0.0,0.0,0.0,0.0,0.0,0.0,0.0,0.0,0.0,0.0,0.0,0.0,0.0,0.0],"24017":[null,null,null,null,null,null,null,null,0.0,0.0,0.0,0.0,0.0,0.0,0.0,0.0,0.0,0.0,0.0,0.0,0.0,0.0,0.0,0.0,0.0,0.0,0.0,0.0],"24025":[null,null,null,null,null,null,null,null,null,null,null,null,null,0.0,0.0,0.0,0.0,0.0,0.0,0.0,0.0,0.0,0.0,0.0,0.0,0.0,0.0,0.0],"24027":[null,null,null,null,null,null,null,null,null,null,0.0,0.0,null,0.0,0.0,0.0,0.0,0.0,0.0,0.0,0.0,0.0,0.0,0.0,0.0,0.0,0.0,0.0],"24031":[0.0,0.0,null,null,null,null,null,null,null,null,null,0.0,null,0.0,0.0,0.0,0.0,0.0,0.0,0.0,0.0,0.0,0.0,0.0,0.0,0.0,0.0,0.0],"24033":[null,null,null,null,null,null,null,null,0.0,0.0,0.0,0.0,0.0,0.0,0.0,0.0,0.0,0.0,0.0,0.0,0.0,0.0,0.0,0.0,0.0,0.0,0.0,0.0],"24510":[0.0,0.0,0.0,0.0,0.0,0.0,0.0,0.0,0.0,0.0,0.0,0.0,0.0,0.0,0.0,0.0,0.0,0.0,0.0,0.0,0.0,0.0,0.0,0.0,0.0,0.0,0.0,0.0],"25005":[null,null,null,0.0,null,null,null,null,null,null,null,null,null,null,null,null,null,null,null,null,null,null,null,null,null,null,null,null],"25009":[null,null,null,null,null,null,null,null,null,null,null,null,null,null,null,null,null,null,null,null,0.0,null,null,null,null,null,null,null],"25013":[null,0.0,0.0,0.0,0.0,0.0,0.0,0.0,null,0.0,0.0,0.0,null,null,null,null,0.0,null,null,null,null,null,null,null,null,null,null,null],"25017":[0.0,0.0,0.0,0.0,0.0,0.0,0.0,0.0,0.0,0.0,0.0,0.0,0.0,0.0,0.0,0.0,0.0,0.0,0.0,0.0,0.0,0.0,0.0,0.0,0.0,0.0,0.0,0.0],"25025":[0.01,0.01,0.01,0.01,0.01,0.01,0.01,0.01,0.01,0.0,0.0,0.01,0.0,0.01,0.01,0.01,0.01,0.01,0.01,0.01,0.01,0.0,0.0,0.0,0.0,0.0,0.0,0.0],"25027":[null,0.0,null,null,null,0.0,null,0.0,null,null,null,null,null,null,null,null,null,null,null,null,null,null,null,null,null,null,null,null],"26007":[null,null,null,null,null,null,null,null,0.0,null,0.0,null,0.0,0.0,null,null,0.01,0.01,0.01,0.01,0.01,0.0,0.0,0.0,0.0,0.0,null,null],"26017":[0.0,0.0,0.0,0.0,null,null,null,null,null,null,null,null,null,null,null,null,null,null,null,null,null,null,null,null,null,null,null,null],"26025":[0.02,0.02,0.02,0.02,0.02,0.02,0.02,0.01,0.01,0.0,0.01,0.0,0.01,0.01,0.01,0.01,0.01,0.01,0.01,0.01,0.0,0.0,0.0,0.0,0.0,0.0,0.0,0.0],"26035":[0.0,null,null,null,null,null,null,null,null,null,0.0,null,null,null,null,null,null,0.0,null,null,null,0.0,0.0,0.0,0.0,0.0,0.0,0.0],"26057":[0.0,0.0,0.0,0.0,0.01,0.0,0.01,0.0,0.0,0.0,0.01,0.01,0.01,0.01,0.01,0.01,0.02,0.02,0.01,0.01,0.01,0.01,0.01,0.01,0.01,0.01,0.01,0.01],"26077":[0.01,0.01,0.01,0.01,0.01,0.01,0.01,0.01,0.01,0.0,0.01,0.02,0.02,0.02,0.01,0.01,0.01,0.01,0.01,0.0,0.0,0.0,0.0,0.0,0.0,0.0,0.0,0.0],"26081":[0.0,0.0,0.0,0.0,0.0,0.0,0.0,0.0,0.0,0.0,0.0,0.0,0.0,0.0,0.0,0.0,0.0,0.0,0.0,0.0,0.0,0.0,0.0,0.0,0.0,0.0,0.0,0.0],"26099":[0.0,null,null,null,0.0,null,null,null,null,null,null,null,null,null,null,null,null,null,null,null,null,null,null,null,null,null,null,null],"26121":[null,null,null,null,null,null,null,null,null,null,null,null,null,null,null,null,0.0,0.0,null,null,null,null,null,null,null,null,null,null],"26145":[0.0,null,null,0.0,null,null,null,null,null,null,null,null,null,null,null,null,null,null,null,null,null,null,null,null,null,null,null,null],"26159":[null,null,0.0,0.0,0.0,0.0,0.0,0.0,0.0,0.0,0.0,0.0,0.0,0.0,0.0,0.0,0.0,0.0,0.0,0.0,0.01,0.0,0.0,0.0,0.01,0.01,0.0,0.0],"26161":[0.0,0.0,null,null,0.0,null,null,null,0.0,null,0.0,null,0.0,null,0.0,0.0,null,0.0,null,0.0,0.0,0.0,0.0,0.0,0.0,0.0,0.0,0.0],"26163":[0.0,0.0,0.0,0.0,null,null,null,null,null,null,null,null,null,null,null,null,null,0.0,null,null,null,null,null,null,null,null,null,null],"27053":[0.0,0.0,0.0,0.0,0.0,0.0,0.0,0.0,0.0,null,null,null,null,null,null,null,null,null,null,null,null,null,null,null,null,null,null,null],"28033":[0.01,0.01,0.01,0.01,0.01,0.01,0.01,0.0,null,null,null,null,null,null,null,null,null,null,null,null,null,null,null,null,null,null,null,null],"28049":[0.0,null,null,null,null,null,null,null,null,null,null,null,null,null,null,null,null,null,null,null,null,null,null,null,null,null,null,null],"28073":[0.01,null,0.01,0.01,0.02,0.02,0.02,0.02,0.01,null,0.01,0.02,0.02,0.02,0.0,0.0,0.01,0.01,0.0,0.01,0.01,0.0,null,0.0,null,null,0.0,null],"28085":[0.03,0.04,0.01,0.01,null,null,0.01,null,null,null,null,null,null,null,null,null,null,null,null,null,null,null,null,null,null,null,null,null],"28133":[null,null,null,null,null,null,0.01,null,null,null,null,null,null,null,null,null,null,null,null,null,null,null,null,null,null,null,null,null],"28151":[0.01,0.01,0.0,0.0,0.01,0.0,null,null,null,null,null,null,null,0.01,null,null,null,null,null,0.0,null,null,null,null,null,null,0.0,0.0],"29189":[0.0,0.0,0.0,0.0,0.0,0.0,0.0,0.0,0.0,null,null,null,null,null,null,null,null,0.0,0.0,0.0,0.0,null,null,null,null,null,null,null],"29201":[null,0.1,null,null,0.04,null,null,null,null,null,0.0,0.0,null,null,0.0,0.0,0.0,0.01,0.01,null,0.02,0.0,0.0,0.01,0.01,null,null,null],"30013":[0.0,0.0,0.0,0.0,0.0,0.0,0.0,0.0,null,0.0,0.0,null,null,0.0,null,0.0,0.0,0.0,null,null,null,null,null,null,null,null,0.0,null],"30101":[null,null,null,null,null,null,null,0.0,null,null,null,null,null,null,null,null,null,null,null,null,null,null,null,null,null,null,null,null],"31055":[0.01,0.0,0.0,0.0,0.0,0.01,0.0,0.0,0.0,0.0,0.0,0.0,0.0,0.0,0.0,0.0,0.0,0.0,0.0,0.0,0.0,0.0,null,null,null,null,null,null],"32003":[0.0,0.0,0.0,0.0,0.0,0.0,0.0,0.0,0.0,0.0,0.0,0.0,0.0,0.0,0.0,0.0,0.0,null,0.0,0.0,0.0,0.0,null,null,0.0,null,null,0.0],"34003":[0.0,0.0,0.0,0.0,0.0,0.0,0.0,0.0,0.0,0.0,0.0,0.0,0.0,0.0,0.0,0.0,0.0,null,null,null,0.0,0.0,0.0,0.0,0.0,null,0.0,null],"34021":[0.0,0.0,0.0,0.0,0.0,0.0,0.0,0.0,0.0,null,null,null,0.0,0.0,0.0,0.0,0.0,0.0,null,null,null,null,null,null,null,null,null,null],"34023":[null,null,null,null,null,null,null,null,null,null,null,null,null,null,null,null,0.0,0.0,0.0,0.0,null,null,null,null,null,null,null,null],"34031":[0.01,0.01,0.01,0.01,0.01,0.01,0.01,0.01,0.01,0.0,0.01,0.01,0.0,0.01,0.01,0.01,0.01,0.01,0.01,0.01,0.01,0.01,0.01,0.01,0.01,0.01,0.01,0.0],"35001":[0.0,0.0,null,0.0,0.0,null,0.0,0.0,null,null,0.0,0.0,0.0,null,null,null,null,0.0,0.0,0.0,0.0,null,0.0,null,null,null,null,null],"36005":[null,null,null,null,null,null,null,null,null,null,null,null,null,null,null,null,null,null,null,null,null,null,0.0,null,null,null,null,null],"36007":[null,null,null,null,null,null,null,null,null,null,null,0.0,null,null,null,null,null,null,null,null,null,null,null,null,null,null,null,null],"36029":[null,null,null,null,null,null,null,null,null,null,null,null,null,null,null,null,null,null,null,null,null,0.0,0.0,null,null,null,null,null],"36047":[null,null,null,null,null,0.0,0.0,0.0,0.0,0.0,0.0,0.0,0.0,0.0,0.0,0.0,0.0,0.0,0.0,0.0,0.0,0.0,0.0,0.0,0.0,0.0,0.0,0.0],"36055":[0.0,0.0,null,0.0,null,null,0.0,0.0,0.0,null,0.0,0.0,null,null,null,null,null,null,null,null,null,null,null,null,null,null,null,null],"36059":[0.0,0.01,0.0,0.0,0.0,0.0,0.0,0.0,0.0,0.0,0.0,0.0,0.0,0.0,0.0,0.0,0.0,0.0,0.0,0.0,0.0,0.0,0.0,0.0,0.0,0.0,0.0,0.0],"36061":[null,null,null,null,0.0,null,null,null,null,null,null,null,null,null,null,null,null,null,null,null,0.0,0.0,0.0,0.0,0.0,0.0,null,null],"36081":[0.0,0.0,0.0,0.0,0.0,0.0,0.0,0.0,0.0,null,0.0,0.0,0.0,0.0,0.0,0.0,0.0,0.0,0.0,0.0,0.0,0.0,0.0,0.0,null,null,null,null],"36083":[null,null,null,null,null,null,null,0.0,null,null,null,0.0,null,0.0,null,null,0.0,null,0.0,null,null,null,null,null,null,null,null,null],"37021":[null,null,null,null,0.0,0.0,null,0.0,null,null,null,0.0,0.0,0.0,0.0,0.0,null,null,null,null,0.0,null,null,null,null,null,null,null],"37047":[null,null,null,0.0,null,0.0,null,null,null,null,null,null,null,null,null,null,null,null,null,null,null,null,null,null,null,null,null,null],"37051":[null,null,null,null,0.0,0.0,0.0,0.0,0.0,0.0,0.0,0.0,0.0,0.0,0.0,0.0,0.0,0.0,0.0,0.0,0.0,0.0,0.0,0.0,0.01,0.0,0.0,0.0],"37063":[null,null,null,null,null,null,null,null,null,null,null,null,null,null,null,null,null,null,null,0.0,null,null,null,null,null,0.0,null,null],"37105":[0.0,0.0,0.01,null,null,null,0.0,0.0,0.0,null,null,0.0,null,null,null,null,null,null,null,null,0.01,0.01,null,null,null,null,null,null],"37119":[0.0,null,0.0,null,0.0,0.0,0.0,0.0,0.0,0.0,0.0,0.0,0.0,0.0,0.0,0.0,0.0,0.0,0.0,null,null,0.0,0.0,0.0,0.0,0.0,0.0,0.0],"37133":[0.0,0.0,null,null,0.0,0.0,0.01,0.0,0.0,0.0,null,null,0.01,0.01,0.02,0.01,0.01,0.01,0.01,0.02,0.01,0.01,0.01,0.01,0.01,0.01,0.02,0.02],"37147":[0.01,0.01,0.0,null,null,null,null,null,null,null,null,null,null,null,null,null,null,null,null,null,null,null,null,null,null,null,null,null],"37155":[null,null,null,null,null,0.0,0.0,0.0,0.0,null,0.0,0.0,null,null,null,null,0.0,null,0.01,null,null,0.01,0.01,0.01,0.0,0.0,0.01,0.0],"37165":[null,null,null,null,0.0,0.01,0.24,0.0,0.03,null,0.0,0.01,0.01,0.07,0.1,0.12,0.14,0.07,0.01,0.06,0.01,0.01,0.03,0.02,0.03,0.03,0.02,0.01],"39003":[null,null,null,null,null,null,null,null,null,null,null,null,null,null,null,null,null,null,null,null,0.01,0.0,0.0,0.0,0.0,0.0,0.0,0.0],"39035":[0.0,0.0,null,null,null,null,null,null,null,null,null,null,null,null,null,null,null,null,null,0.0,null,null,null,null,null,null,null,null],"39041":[0.01,0.01,null,null,null,null,null,null,null,null,null,null,null,null,null,null,null,null,null,null,null,null,0.01,0.0,null,null,null,null],"39049":[0.0,0.0,0.0,0.0,0.0,0.0,0.0,0.0,0.0,0.0,0.0,0.0,0.0,0.0,0.0,0.0,0.0,0.0,0.0,0.0,0.0,0.0,0.0,0.0,0.0,0.0,0.0,0.0],"39061":[0.01,0.01,0.01,0.01,0.01,0.01,0.01,0.01,0.01,0.0,0.01,0.01,0.01,0.01,0.01,0.01,0.01,0.02,0.01,0.01,0.01,0.02,0.02,0.01,0.01,0.02,0.01,null],"39089":[0.0,0.0,0.01,0.01,0.0,0.01,0.01,0.0,0.0,0.0,0.0,0.0,0.01,0.0,0.01,0.01,null,null,null,null,null,null,null,null,null,null,null,null],"39093":[null,null,null,null,null,null,null,null,null,null,null,null,null,null,null,null,null,null,null,null,null,null,null,null,null,null,0.0,null],"39113":[0.0,0.0,null,0.0,null,0.0,null,null,null,null,0.0,0.0,0.0,0.0,0.0,0.0,0.0,0.0,0.0,null,0.0,0.0,0.0,null,0.0,null,null,null],"39139":[null,null,null,null,null,null,null,null,null,null,null,null,null,null,null,null,null,null,null,null,0.0,null,null,null,null,null,null,0.0],"39153":[null,0.0,null,null,null,null,0.0,null,null,null,null,null,null,null,null,null,null,null,null,null,null,null,null,null,null,null,null,null],"39155":[0.04,0.04,0.04,0.04,0.04,0.04,0.04,0.04,0.04,0.04,0.05,0.05,0.05,0.04,0.04,0.04,0.04,0.03,0.03,0.02,null,null,null,null,null,null,null,null],"40109":[0.0,0.0,null,null,null,null,0.0,null,0.0,null,0.0,0.0,null,null,null,null,null,null,null,null,null,null,null,null,null,null,null,null],"41029":[0.0,null,null,null,null,null,null,null,null,null,null,null,null,null,null,null,null,null,null,0.0,null,null,null,null,null,null,null,null],"41043":[0.0,null,null,null,null,null,null,null,null,null,null,null,null,null,null,null,null,null,null,null,null,null,null,null,null,null,null,null],"41047":[null,null,null,null,0.0,null,null,null,0.0,null,null,null,null,null,null,null,null,0.0,null,null,null,null,null,null,null,null,null,null],"41059":[0.03,0.03,0.02,0.01,0.01,0.01,0.01,0.01,0.01,0.01,0.01,0.0,null,null,0.0,0.0,0.01,0.01,0.01,0.0,0.0,0.01,0.0,0.01,0.01,0.0,0.01,null],"42003":[null,null,null,null,0.0,0.0,null,null,null,0.0,null,0.0,0.0,0.0,0.0,0.0,0.0,0.0,0.0,0.0,0.0,null,0.0,0.0,0.0,null,null,null],"42013":[null,null,null,null,null,null,null,null,null,null,null,0.0,0.0,0.0,0.0,0.0,0.0,null,null,null,null,0.0,0.0,0.0,0.0,0.0,0.0,null],"42043":[null,null,null,null,null,null,null,null,null,0.0,null,null,null,null,null,null,null,null,null,null,null,null,null,null,0.0,null,null,null],"42077":[null,null,null,null,null,null,null,null,null,null,null,null,null,null,null,null,0.0,null,0.0,0.0,0.0,0.0,0.0,0.0,0.0,0.0,0.0,0.0],"42091":[0.0,0.0,0.0,0.0,0.0,0.0,0.0,0.0,0.0,null,null,null,0.0,0.0,0.0,null,null,null,null,null,null,null,null,null,null,null,0.0,null],"45003":[null,null,null,0.01,null,null,null,null,null,null,null,null,null,null,null,null,null,null,null,null,null,null,null,null,null,null,null,null],"45051":[null,null,0.0,0.0,0.0,null,null,null,null,null,null,null,null,null,null,null,null,null,null,null,null,null,null,null,null,null,null,null],"45057":[0.0,0.0,0.0,0.0,0.0,0.0,0.0,null,null,null,null,null,null,null,null,null,null,null,null,null,null,null,null,null,null,null,null,null],"45071":[0.02,0.01,0.03,0.02,0.02,0.02,null,0.0,0.02,0.03,0.04,0.03,0.03,0.03,0.03,0.02,0.02,0.01,null,null,null,null,null,null,null,null,null,null],"45079":[0.0,null,0.0,0.0,null,0.0,null,null,0.0,null,0.0,0.0,0.0,null,null,null,null,null,null,null,null,null,null,null,null,null,null,null],"46099":[null,null,null,null,null,null,null,null,null,null,null,null,null,null,null,null,null,null,null,null,0.0,null,null,null,null,null,null,0.0],"46103":[null,null,null,null,null,null,null,null,null,null,null,null,null,null,null,null,null,null,0.01,0.01,null,null,null,null,null,null,null,null],"47037":[null,0.0,null,null,null,null,null,null,null,null,null,null,null,null,null,null,null,null,null,null,null,null,null,null,null,null,null,null],"47045":[null,null,null,null,null,null,null,null,0.0,0.01,0.01,0.01,null,0.01,0.01,0.0,null,null,null,null,null,null,null,null,null,null,null,null],"47093":[0.0,0.0,0.0,0.0,null,0.0,null,null,null,null,null,null,0.0,null,0.0,0.0,null,null,null,null,null,null,null,null,null,null,null,null],"47125":[null,null,null,null,null,null,null,null,0.0,null,null,null,null,null,null,null,null,null,null,null,null,null,null,null,null,null,null,null],"47157":[null,0.0,null,0.0,null,0.0,0.0,null,null,null,null,null,null,null,null,null,null,null,null,null,null,null,null,null,null,null,null,null],"48029":[null,null,null,null,null,null,null,null,null,null,null,0.0,null,null,null,null,null,null,null,null,null,null,null,null,null,null,null,null],"48061":[null,null,null,null,null,null,null,null,0.0,0.0,0.0,0.0,0.0,0.0,0.0,0.0,0.0,0.0,0.0,0.0,0.0,0.0,null,null,null,null,null,null],"48085":[null,null,null,null,null,null,null,null,null,null,null,0.0,0.0,0.0,0.0,0.0,0.0,0.0,0.0,0.0,0.0,0.0,0.0,null,null,null,null,null],"48113":[null,0.0,null,0.0,0.0,0.0,0.0,0.0,0.0,null,0.0,0.0,0.01,0.01,0.0,0.0,0.0,0.01,0.0,0.0,0.0,0.0,0.0,0.0,0.0,0.0,0.0,0.0],"48141":[null,null,null,null,null,null,null,null,null,null,null,null,0.0,0.0,0.0,0.0,0.0,0.0,0.0,0.0,0.0,0.0,0.0,0.0,0.0,0.0,0.0,null],"48167":[null,null,null,null,null,null,null,null,null,null,null,null,null,null,null,null,null,null,null,null,null,null,null,0.01,null,null,null,null],"48201":[null,0.0,0.0,0.0,0.0,0.0,0.0,null,null,null,0.0,null,null,null,null,null,0.0,null,null,null,0.0,null,null,null,null,null,null,null],"48215":[null,null,null,null,null,null,null,null,null,null,null,0.0,0.0,0.0,0.0,0.0,0.0,0.0,0.0,0.0,0.0,0.0,0.0,null,0.0,0.0,0.0,0.0],"48423":[null,null,null,null,null,null,null,null,null,null,null,null,0.0,0.0,null,null,null,null,null,null,null,null,null,null,null,null,null,null],"48453":[null,null,null,null,null,null,null,null,null,null,null,null,null,null,null,null,null,0.0,null,null,0.0,0.0,0.0,0.0,0.0,0.0,0.0,0.0],"48465":[null,null,null,null,null,null,null,null,null,null,null,null,null,null,null,null,null,null,null,null,0.0,0.0,null,null,null,null,null,null],"49011":[null,null,null,null,null,0.0,null,null,null,null,null,null,null,null,null,null,null,null,null,null,null,null,null,null,null,null,null,null],"50023":[null,null,null,0.0,null,null,null,null,null,null,null,null,null,null,null,null,null,null,null,null,null,null,null,null,null,null,null,null],"51015":[null,null,null,null,null,0.0,null,0.0,null,null,null,null,null,null,null,null,null,null,null,0.01,0.01,0.01,0.01,null,0.0,null,null,null],"51041":[null,null,null,null,null,null,null,null,null,null,null,null,null,null,null,null,null,null,null,null,null,0.0,null,null,null,null,null,null],"51059":[null,0.0,0.0,null,null,null,null,null,0.0,0.0,0.0,0.0,0.0,0.0,null,null,null,null,null,null,null,null,null,null,null,0.0,0.0,null],"51087":[0.01,0.01,0.02,0.02,0.02,0.03,0.04,0.03,0.04,0.04,0.05,0.06,0.05,0.05,0.06,0.06,0.06,0.07,0.07,0.06,0.08,0.09,0.08,0.06,0.02,0.01,0.01,0.01],"51117":[0.0,0.0,0.0,null,0.0,0.0,0.0,0.0,0.0,null,0.01,0.0,0.0,0.0,null,null,0.0,null,0.0,null,null,null,0.0,null,null,null,null,null],"51153":[null,null,null,null,null,null,null,null,null,null,null,null,null,null,null,null,null,null,null,null,null,null,0.0,null,null,null,null,null],"51550":[null,null,null,0.0,0.0,0.0,0.0,0.0,0.0,0.0,0.0,0.0,0.0,0.0,0.0,0.0,0.0,0.0,0.0,0.0,0.0,0.01,0.0,0.0,0.0,0.01,0.0,0.0],"51630":[null,null,0.02,null,null,0.02,null,null,null,null,null,null,null,null,null,null,null,0.01,0.01,0.01,null,null,0.02,null,null,null,null,null],"51650":[null,null,null,0.0,0.0,0.0,0.0,0.0,0.0,0.0,0.0,0.0,0.0,0.0,0.0,0.0,0.0,0.01,0.0,0.0,0.01,0.01,0.01,0.01,0.01,0.01,0.01,0.0],"51700":[null,null,null,null,null,null,0.0,null,null,null,null,null,null,0.0,null,0.0,0.0,0.0,0.0,0.0,0.0,0.0,0.0,0.0,0.0,0.0,0.0,null],"51710":[null,null,null,null,null,null,0.0,null,null,null,null,null,null,null,0.0,null,null,null,null,null,null,0.0,0.0,null,0.0,null,0.0,null],"51760":[null,null,null,null,null,null,null,null,null,null,null,null,null,null,null,null,null,null,0.0,null,0.0,0.0,0.0,null,0.0,0.0,0.0,null],"51810":[null,null,0.0,null,null,null,0.0,0.0,0.0,0.0,0.0,0.0,0.0,0.0,0.0,0.0,0.0,0.0,0.01,0.01,0.01,0.01,0.01,0.01,0.01,0.01,0.01,0.0],"53005":[null,null,null,null,0.0,0.0,0.0,0.01,0.01,0.0,0.01,0.01,0.01,0.01,0.01,0.01,0.01,0.02,0.01,0.01,0.01,0.01,0.01,0.01,0.01,0.01,0.01,0.01],"53033":[0.0,0.0,0.0,0.0,0.0,0.0,0.0,0.0,0.0,0.0,0.0,0.0,0.0,0.0,0.0,0.0,0.0,0.0,0.0,0.0,0.0,0.0,0.0,0.0,null,0.0,0.0,0.0],"53047":[null,null,null,null,null,null,null,null,null,0.02,0.03,null,0.01,null,null,null,null,null,null,null,0.01,0.01,null,null,null,null,0.01,null],"53051":[0.04,null,null,null,0.1,0.04,0.08,0.13,0.05,null,null,null,null,null,null,null,null,null,null,null,null,null,null,null,null,null,null,null],"53053":[null,null,null,null,0.0,null,null,null,null,null,null,null,null,null,0.0,null,0.0,0.0,0.0,null,0.0,0.0,0.0,0.0,0.0,null,0.0,0.0],"53061":[0.0,0.0,0.0,0.0,0.0,0.0,null,null,null,null,null,null,null,null,null,null,null,null,null,null,null,null,null,null,null,null,null,null],"53063":[0.01,0.0,0.0,0.0,0.0,0.0,0.0,0.0,null,null,null,null,null,null,0.0,0.0,0.0,0.0,0.0,null,null,null,null,null,null,null,null,null],"53077":[null,null,null,null,null,null,null,null,null,null,null,null,0.0,0.0,null,0.0,0.0,0.0,0.0,null,null,0.0,0.0,0.0,null,0.0,0.0,0.0],"54067":[null,null,0.02,null,null,null,null,null,null,null,null,null,null,null,null,null,null,null,null,null,null,null,null,null,null,null,null,null],"55025":[null,null,null,null,null,null,null,null,null,null,null,null,null,null,null,null,null,null,0.0,null,0.0,null,null,null,null,null,null,null],"55029":[null,null,null,null,null,null,null,null,null,null,null,null,null,null,null,null,null,null,0.01,null,null,null,null,null,null,null,null,null],"55063":[null,null,null,0.02,null,null,null,null,null,null,null,null,null,0.04,0.0,null,0.0,null,null,null,null,0.0,0.0,null,0.01,null,0.01,null],"55079":[null,0.0,0.0,0.0,0.0,null,0.0,null,0.0,null,null,null,null,null,null,null,null,null,null,null,null,null,null,null,0.0,null,null,null],"55081":[null,null,null,null,null,null,null,null,0.01,null,null,null,null,null,null,null,null,null,0.01,0.01,0.01,0.01,0.0,0.01,0.0,null,0.0,null],"55103":[null,null,null,null,null,null,null,null,null,null,null,null,null,null,null,null,0.01,null,null,null,null,null,null,0.04,null,0.02,null,0.02],"55111":[0.02,null,0.01,null,0.01,null,null,0.01,0.01,null,0.01,0.01,0.01,0.01,0.02,0.03,0.03,0.02,0.01,0.03,0.03,0.04,0.03,0.02,null,null,null,null]}